molsaic/__init__.py
molsaic-0.1.0.dist-info/METADATA
molsaic-0.1.0.dist-info/WHEEL
molsaic-0.1.0.dist-info/RECORD
