Metadata-Version: 2.1
Name: molsaic
Version: 0.1.0
Summary: Python package for performing cluster-cutout calculations
License: Apache-2.0
Author: Fabian Zills
Author-email: fzills@icp.uni-stuttgart.de
Requires-Python: >=3.11,<4.0
Classifier: License :: OSI Approved :: Apache Software License
Classifier: Programming Language :: Python :: 3
Classifier: Programming Language :: Python :: 3.11
Classifier: Programming Language :: Python :: 3.12
Requires-Dist: ase (>=3.23.0,<4.0.0)
Requires-Dist: networkx (>=3.4.1,<4.0.0)
